[
  {
    "type": "video",
    "file_id": "BAACAgQAAx0CYk8gEQACCVlogAb2r0o3mDz-cof30ymUCwXcMgAC5hgAAk2H2FD-VSkdfMjcXjYE",
    "caption": "๐ข ุจุฑูุงูู ุงูฺฉูุงุณฺฉูุ ุจู ุฑูุงุช ุชุณูุง ูุณูุช ููุชู\n๐ฅย ููููุช 480"
  },
  {
    "type": "video",
    "file_id": "BAACAgQAAx0CYk8gEQACCVtogAb2Zqf3IXQxOp9IGvDKL7HBPQACJxoAAtDdIFHWeKxRnREJhTYE",
    "caption": "๐ข ุจุฑูุงูู ุงูฺฉูุงุณฺฉูุ ุจู ุฑูุงุช ุชุณูุง ูุณูุช ูุดุชู\n๐ฅย ููููุช 480"
  },
  {
    "type": "video",
    "file_id": "BAACAgQAAx0CYk8gEQACCV1ogAb2eIaBQmgUWfWAffbdXhJi7AACuxwAAs6uaVF_798n_RFYZDYE",
    "caption": "๐ฅ #ุจุฑูุงูู ยซุงูฺฉูุงุณฺฉูุ ุจู ุฑูุงุช ุชุณูุงยป \n๐ฏ ูุณูุชย9\nโ๏ธ ูุณุฎู ุงูุฑุฌูุงู\n๐ ููุถูุน: ูุณุงุจูู | ูุนูุง | ุฎุงููุงุฏฺฏ \n๐ ฺฉูุช 480p"
  },
  {
    "type": "video",
    "file_id": "BAACAgQAAx0CYk8gEQACCWJogAb28V00mkaKYIVJSvEcJ626mwACGxYAAlAguVF30aEObz_lIzYE",
    "caption": "๐ข ุจุฑูุงูู ุงูฺฉูุงุณฺฉูุ ุจู ุฑูุงุช ุชุณูุง ูุณูุช ุฏูู\n๐ฅย ููููุช 480"
  },
  {
    "type": "video",
    "file_id": "BAACAgQAAx0CYk8gEQACCWRogAb2yFeqR-Ran-BPTkCLEc6BXAACYBkAAvB52VJN4R5p29JcJjYE",
    "caption": "๐ข ุจุฑูุงูู ุงูฺฉูุงุณฺฉูุ ุจู ุฑูุงุช ุชุณูุง ูุณูุช ุงุฒุฏูู\n๐ฅย ููููุช 480"
  },
  {
    "type": "video",
    "file_id": "BAACAgQAAx0CYk8gEQACCWZogAb2wGgqnvSbuxB1JDfQT__n2AAC5RgAAr0hKVNc_mXrGA5jijYE",
    "caption": "๐ข ุจุฑูุงูู ุงูฺฉูุงุณฺฉูุ ุจู ุฑูุงุช ุชุณูุง ูุณูุช ุฏูุงุฒุฏูู\n๐ฅย ููููุช 480"
  }
]